geoextract/__init__.py
geoextract/app.py
tests/__init__.py
tests/test_app.py
tests/test_example.py
tests/test_geoextract.py
geoextract-0.3.1.dist-info/LICENSE
geoextract-0.3.1.dist-info/METADATA
geoextract-0.3.1.dist-info/WHEEL
geoextract-0.3.1.dist-info/top_level.txt
geoextract-0.3.1.dist-info/RECORD
