Metadata-Version: 2.1
Name: geoextract
Version: 0.3.1
Summary: Extraction of locations from plain text
Home-page: https://github.com/stadt-karlsruhe/geoextract
Author: Stadt Karlsruhe
Author-email: transparenz@karlsruhe.de
License: MIT
Keywords: location,address,extraction
Platform: UNKNOWN
Classifier: Development Status :: 4 - Beta
Classifier: License :: OSI Approved :: MIT License
Classifier: Programming Language :: Python :: 2.7
Requires-Dist: Flask (>=0.12.1)
Requires-Dist: nltk (>=3.2.2)
Requires-Dist: numpy (>=1.11.0)
Requires-Dist: pyahocorasick (>=1.1.4)
Requires-Dist: scipy (>=0.17.0)
Requires-Dist: six (>=1.10.0)
Requires-Dist: unidecode (>=0.4.21)
